{
  "name": {
    "text": {
      "translate": "Electric Sander"
    }
  },
  "appearance": {
    "running": {
      "custommachinery:ambient_sound": {
        "sound": "minecraft:block.furnace.fire_crackle"
      }
    },
    "custommachinery:block": "custommachinery:machine/electric_sander",
    "custommachinery:mining_level": "minecraft:needs_stone_tool",
    "custommachinery:requires_tool": false
  },
  "components": [
    {
      "type": "custommachinery:energy",
      "capacity": 10000
    },
    {
      "type": "custommachinery:item",
      "config": {
        "TOP": "INPUT",
        "BOTTOM": "INPUT",
        "FRONT": "INPUT",
        "RIGHT": "INPUT",
        "BACK": "INPUT",
        "LEFT": "INPUT"
      },
      "id": "input",
      "mode": "input"
    },
    {
      "type": "custommachinery:item",
      "config": {
        "TOP": "OUTPUT",
        "BOTTOM": "OUTPUT",
        "FRONT": "OUTPUT",
        "RIGHT": "OUTPUT",
        "BACK": "OUTPUT",
        "LEFT": "OUTPUT"
      },
      "id": "output",
      "mode": "output"
    }
  ],
  "gui": [
    {
      "type": "custommachinery:background",
      "width": 172,
      "height": 160
    },
    {
      "type": "custommachinery:energy",
      "x": 5,
      "y": 37,
      "width": 18,
      "height": 40
    },
    {
      "type": "custommachinery:player_inventory",
      "x": 5,
      "y": 78
    },
    {
      "type": "custommachinery:progress",
      "x": 74,
      "y": 39
    },
    {
      "type": "custommachinery:slot",
      "id": "input",
      "x": 48,
      "y": 38
    },
    {
      "type": "custommachinery:slot",
      "id": "output",
      "x": 107,
      "y": 35,
      "width": 25,
      "height": 25
    },
    {
      "type": "custommachinery:text",
      "x": 46,
      "y": 4,
      "text": {
        "text": {
          "translate": "Electric Sander"
        },
        "color": "dark_gray"
      }
    }
  ],
  "tooltips": {
    "text": {
      "translate": "WORK IN PROGRESS"
    }
  }
}